{
    "maps": [
        { "category": "village", "value": "none.png", "text": "None" },
        { "category": "city", "value": "none.png", "text": "None" },
        { "category": "capital", "value": "none.png", "text": "None" },
        { "category": "fortress", "value": "none.png", "text": "None" },
        { "category": "WorldMap", "value": "none.png", "text": "None" },

        { "category": "village", "value": "TW Village 1.webp", "text": "TW Village 1" },
        { "category": "village", "value": "TW Village Westwood.webp", "text": "TW Village Westwood" },
        
        { "category": "city", "value": "Anadoulou City 2D.png", "text": "Anadoulou City 2D" },
        { "category": "city", "value": "Anadoulou City 3D.png", "text": "Anadoulou City 3D" },
        { "category": "city", "value": "White elk fort 2d.png", "text": "Asian 2Breach 2D" },
        { "category": "city", "value": "Asian 2Breach 3D Back.png", "text": "Asian 2Breach 3D Back" },
        { "category": "city", "value": "Asian2 NoBreach 2D.png", "text": "Asian1 NoBreach 2D" },
        { "category": "city", "value": "TW - Sun City.webp", "text": "Asian2 NoBreach 2D" },
        { "category": "city", "value": "European Right Breach 2D.png", "text": "European Right Breach 2D" },
        { "category": "city", "value": "TW Valley Fortress.webp", "text": "European NoBreach (Schaken) 2D" },
        { "category": "city", "value": "European NoBreach (Schaken) 3D Fron.png", "text": "European NoBreach (Schaken) 3D" },

        { "category": "capital", "value": "Anliang 2d.png", "text": "Anliang 2D" },
        { "category": "capital", "value": "Anliang 3D Back.png", "text": "Anliang 3D Back" },
        { "category": "capital", "value": "Anliang 3D Front.png", "text": "Anliang 3D Front" },
        { "category": "capital", "value": "Augolia2D.png", "text": "Augolia 2D" },
        { "category": "capital", "value": "Augolia3D.jpg", "text": "Augolia 3D" },
        { "category": "capital", "value": "CC.webp", "text": "Conqueror's City" },
        { "category": "capital", "value": "CC 3D Front.png", "text": "Conqueror's City 3D Front" },
        { "category": "capital", "value": "Conquerors Gate 3D.png", "text": "Conquerors Gate 3D" },
        { "category": "capital", "value": "TW Gate Roya Ramparts.webp", "text": "Conquerors Gate 2D" },
        { "category": "capital", "value": "Reginopolis 2D.png", "text": "Reginopolis 2D" },
        { "category": "capital", "value": "Reginopolis 3D.png", "text": "Reginopolis 3D" },
        { "category": "capital", "value": "Turul 2D.png", "text": "Turul 2D" },
        { "category": "capital", "value": "Turul 3D.png", "text": "Turl 3D" },

        { "category": "WorldMap", "value": "NorthBorderlands.png", "text": "North Borderlands" },
        { "category": "WorldMap", "value": "SouthBorderlands.png", "text": "South Borderlands" },
        { "category": "WorldMap", "value": "OSTARIA.png", "text": "Ostaria" },
        { "category": "WorldMap", "value": "Ungverija.png", "text": "Ungverija" },

        { "category": "fortress", "value": "Anadoulou Fortress 3d BACK.png", "text": "Anadoulou Fortress 3D Back" },
        { "category": "fortress", "value": "Anadoulou Fortress 3D Front.png", "text": "Anadoulou Fortress 3D Front" },
        { "category": "fortress", "value": "Asian Fort 2d.png", "text": "Asian Fortress 2D" },
        { "category": "fortress", "value": "Asian Fort 3D Front.png", "text": "Asian Fortress 3D Front" },
        { "category": "fortress", "value": "TW - Border Fort.webp", "text": "Asian1 Fortress 2D Front" },
        { "category": "fortress", "value": "Asian1 NoBreach 3D Back.png", "text": "Asian1 Fortress 3D Back" },
        { "category": "fortress", "value": "TW West Fort.webp", "text": "European Fortress 2D" },
        { "category": "fortress", "value": "European Left Breach 3D Front.png", "text": "European Fortress 3D Front" },
        { "category": "fortress", "value": "European Left Breach 3D Back.png", "text": "European Fortress 3D Back" }
    ]
}
